diva_seq_opt/__init__.py
diva_seq_opt/predict_loading_concentration.py
diva_seq_opt/utility.py
diva_seq_opt/model/__init__.py
diva_seq_opt/model/model.pkl
diva_seq_opt/model/model30.pkl
diva_seq_opt/model/model50.pkl
diva_seq_opt-0.0.3.dist-info/LICENSE.txt
diva_seq_opt-0.0.3.dist-info/METADATA
diva_seq_opt-0.0.3.dist-info/WHEEL
diva_seq_opt-0.0.3.dist-info/entry_points.txt
diva_seq_opt-0.0.3.dist-info/top_level.txt
diva_seq_opt-0.0.3.dist-info/RECORD
