Metadata-Version: 2.1
Name: diva-seq-opt
Version: 0.0.3
Summary: Predict the library loading concentration to use for mi-seq runs based on bioanalyzer data.
Home-page: https://github.com/JBEI/library_loading_concentration_prediction
Author: Zak Costello
Author-email: zak.costello@gmail.com
License: BSD
Platform: UNKNOWN
Requires-Dist: pandas
Requires-Dist: numpy
Requires-Dist: scipy
Requires-Dist: matplotlib
Requires-Dist: peakutils
Requires-Dist: sklearn
Requires-Dist: tpot
